k8s_uwsgi/__init__.py
k8s_uwsgi/pod_utils.py
uwsgi_readiness_check-0.2.0.dist-info/LICENSE
uwsgi_readiness_check-0.2.0.dist-info/METADATA
uwsgi_readiness_check-0.2.0.dist-info/WHEEL
uwsgi_readiness_check-0.2.0.dist-info/entry_points.txt
uwsgi_readiness_check-0.2.0.dist-info/top_level.txt
uwsgi_readiness_check-0.2.0.dist-info/RECORD
